nuts_finder/__init__.py
nuts_finder/nuts_finder.py
nuts_finder-21.5.5.14.dist-info/LICENSE
nuts_finder-21.5.5.14.dist-info/METADATA
nuts_finder-21.5.5.14.dist-info/WHEEL
nuts_finder-21.5.5.14.dist-info/top_level.txt
nuts_finder-21.5.5.14.dist-info/RECORD
