Metadata-Version: 2.1
Name: nuts-finder
Version: 21.5.5.14
Summary: UNKNOWN
Home-page: https://github.com/nestauk/nuts_finder
Author: Nesta
Author-email: software_development@nesta.org.uk
Maintainer: Nesta
Maintainer-email: software_development@nesta.org.uk
License: MIT
Platform: UNKNOWN
Classifier: Development Status :: 3 - Alpha
Classifier: Intended Audience :: Developers
Classifier: Intended Audience :: Science/Research
Classifier: License :: OSI Approved :: MIT License
Classifier: Natural Language :: English
Classifier: Operating System :: OS Independent
Classifier: Programming Language :: Python :: 3.7
Requires-Python: >3.6
Requires-Dist: geojson (==2.5.0)
Requires-Dist: requests (==2.22.0)
Requires-Dist: Shapely (==1.6.2.post1)
